Metadata-Version: 2.4
Name: inception-fid-weights-zst-shard01
Version: 0.1.0
Summary: Shard 01 for inception-fid-weights-zst
Author: Your Name
Requires-Python: >=3.8
